{
  "id": "stories_adult_v5",
  "title": "Истории — взрослые (разные стили)",
  "questions": [
    {
      "id": "a_noir_01",
      "format": "single",
      "tags": ["aud:adult","style:story","quality:rich","style:noir"],
      "text": "Ночной брифинг (нуар)",
      "intro": "Клиент просит к утру план расследования утечки данных. Доказательств мало, следы путают.",
      "options": [
        {"id":"A","label":"Раскладываю факты, строю версию, фиксирую шаги проверки.","weights":{"G":1.0,"mod_discipline":0.6}},
        {"id":"B","label":"Делаю убедительный питч для совета директоров.","weights":{"K":1.0,"mod_creative":0.6}},
        {"id":"C","label":"Проверяю логи и собираю технические артефакты сам(а).","weights":{"T":1.0,"mod_action":0.8}},
        {"id":"D","label":"Организую людей: кто с кем общается, кого поддержать.","weights":{"S":1.0,"mod_magnetic":0.6}}
      ]
    },
    {
      "id": "a_scifi_01",
      "format": "single",
      "tags": ["aud:adult","style:story","quality:rich","style:scifi"],
      "text": "Орбitalный запуск (sci-fi)",
      "intro": "Прототип спутника готов, окно запуска короткое. Любая задержка — минус месяц.",
      "options": [
        {"id":"A","label":"Собираю чек-лист и последовательность операций.","weights":{"G":1.0,"mod_hinayana":0.4}},
        {"id":"B","label":"Объясняю миссию и вдохновляю команду в трансляции.","weights":{"K":1.0,"mod_mahayana":0.5}},
        {"id":"C","label":"Лично проверяю узлы: питание, телеметрию, привод.","weights":{"T":1.0,"mod_settler":0.6}},
        {"id":"D","label":"Координирую команды наземки и связи.","weights":{"S":1.0,"mod_magnetic":0.5}}
      ]
    },
    {
      "id": "a_thriller_01",
      "format": "single",
      "tags": ["aud:adult","style:story","quality:rich","style:thriller"],
      "text": "Срыв презентации (триллер)",
      "intro": "За 30 минут до питча у ключевого ноутбука умер экран. Клиент уже в лифте.",
      "options": [
        {"id":"A","label":"Моментально перестраиваю сценарий и роли.","weights":{"G":1.0}},
        {"id":"B","label":"Беру речь, держу внимание и тон.","weights":{"K":1.0,"mod_papillon":0.6}},
        {"id":"C","label":"Ставлю запасное устройство и поднимаю демо.","weights":{"T":1.0,"mod_action":0.9}},
        {"id":"D","label":"Раскидываю задачи и поддерживаю команду.","weights":{"S":1.0}}
      ]
    }
  ]
}
